{
    "task_metadata": {
        "task_id": "os_malform_008",
        "domain": "operating_system",
        "failure_category": "malformed_input",
        "target_recovery": "fix_and_retry"
    },
    "environment_setup": {
        "filesystem_state": "Standard Linux user environment",
        "available_tools": [
            "create_user",
            "submit_answer"
        ]
    },
    "evaluation_loop": {
        "condition": "Create a new developer user with UID 1005.",
        "injected_failure_state": {
            "tool": "create_user",
            "payload": "username='dev_user', uid = '1005'",
            "observation": "TypeError: 'uid' parameter requires an integer, received string."
        },
        "success_criteria": "Agent removes the quotation marks around the UID to pass it as an integer and retries."
    }
}